mpdnotify/__init__.py
mpdnotify/cli.py
mpdnotify/config.py
mpdnotify/notify.py
mpdnotify-1.0.dist-info/METADATA
mpdnotify-1.0.dist-info/WHEEL
mpdnotify-1.0.dist-info/entry_points.txt
mpdnotify-1.0.dist-info/top_level.txt
mpdnotify-1.0.dist-info/RECORD
