Metadata-Version: 2.1
Name: mpdnotify
Version: 1.0
Summary: mpdnotify - get notification when changing song
Home-page: https://github.com/chuugar/mpdnotify
Author: chuugar
Author-email: charles-thomas@sfr.fr
License: GPL3
Platform: UNKNOWN
Classifier: Environment :: Console
Classifier: Environment :: Console :: Curses
Classifier: License :: OSI Approved :: GNU General Public License (GPL)
Classifier: Programming Language :: Python :: 3
Classifier: Topic :: Multimedia :: Sound/Audio :: Mixers
Classifier: Topic :: Utilities
Requires-Dist: python-mpd2
Requires-Dist: Pillow
